Metadata-Version: 2.4
Name: AxSI
Version: 0.0.16
Summary: AxSI for MRI data
Home-page: 
Author: Hila Gast
Author-email: 
Classifier: Programming Language :: Python :: 3
Classifier: License :: OSI Approved :: MIT License
Classifier: Operating System :: OS Independent
Requires-Python: >=3.10
Requires-Dist: numpy==1.26.4
Requires-Dist: scipy==1.14.1
Requires-Dist: scikit-learn==1.5.2
Requires-Dist: psutil==6.1.1
Requires-Dist: nibabel==5.3.0
Requires-Dist: dipy==1.9.0
Requires-Dist: lsqAxSI
Requires-Dist: rpy2==3.5.11
Requires-Dist: ecos==2.0.14
Requires-Dist: cvxpy==1.5.3
Requires-Dist: gurobipy==12.0.0
Requires-Dist: dash==2.18.2
Requires-Dist: plotly==5.24.1
Requires-Dist: pandas==2.2.3
Requires-Dist: pytest==8.0
Dynamic: author
Dynamic: classifier
Dynamic: description
Dynamic: description-content-type
Dynamic: requires-dist
Dynamic: requires-python
Dynamic: summary
